LICENSE.txt
MANIFEST.in
README.md
setup.cfg
setup.py
Django_Org_Associations.egg-info/PKG-INFO
Django_Org_Associations.egg-info/SOURCES.txt
Django_Org_Associations.egg-info/dependency_links.txt
Django_Org_Associations.egg-info/requires.txt
Django_Org_Associations.egg-info/top_level.txt
django_associations/__info__.py
django_associations/__init__.py
django_associations/admin.py
django_associations/settings.py
django_associations/signals.py
django_associations/urls.py
django_associations/views.py
django_associations/management/__init__.py
django_associations/management/commands/__init__.py
django_associations/migrations/0001_initial.py
django_associations/migrations/__init__.py
django_associations/models/__init__.py
django_associations/models/abstracts.py
django_associations/models/core.py
django_associations/tools/__init__.py
django_associations/tools/models.py
django_associations/tools/relation.py
interface/__init__.py
interface/settings.py
interface/urls.py
interface/wsgi.py