Metadata-Version: 1.1
Name: Django-Org-Associations
Version: 0.1.3
Summary: Django Organisation/Member associations
Home-page: https://github.com/blancltd/django-associations
Author: Martin P. Hellwig
Author-email: martin.hellwig@gmail.com
License: BSD
Download-URL: https://github.com/blancltd/django-associations/archive/master.zip
Keywords: django
Platform: any
Classifier: Programming Language :: Python :: 3
Classifier: Environment :: Web Environment
Classifier: Framework :: Django
Classifier: Framework :: Django :: 1.9
Classifier: License :: OSI Approved :: BSD License
Classifier: Operating System :: OS Independent
